[
  {
    "id": "sefaria-psalm-042-deep-calls-to-deep",
    "sourceId": "sefaria-psalms",
    "status": "review-needed",
    "category": "Psalms",
    "artifact": "Psalm 42 — Deep Calls to Deep",
    "original": "Psalm 42:7: deep calls unto deep in the sound of waters.",
    "english": "Depth does not answer surface; it calls to what is already deep enough to hear.",
    "spanish": "La profundidad no responde a la superficie; llama a lo que ya es bastante hondo para oír.",
    "recommendedEditionSource": "Sefaria — Psalms 42:7",
    "sourceUrl": "https://www.sefaria.org/Psalms.42.7",
    "notes": "Real capture from public web source. Review-needed: confirm Hebrew/KJV/Spanish witness alignment before promotion. Short paraphrase only."
  },
  {
    "id": "sefaria-psalm-046-be-still",
    "sourceId": "sefaria-psalms",
    "status": "review-needed",
    "category": "Psalms",
    "artifact": "Psalm 46 — Be Still",
    "original": "Psalm 46:10: stillness is joined to knowing.",
    "english": "Knowledge begins where agitation stops performing itself.",
    "spanish": "El conocimiento empieza donde la agitación deja de representarse a sí misma.",
    "recommendedEditionSource": "Sefaria — Psalms 46:10",
    "sourceUrl": "https://www.sefaria.org/Psalms.46.10",
    "notes": "Real capture from public web source. Review-needed: confirm verse rendering before promotion."
  },
  {
    "id": "sefaria-psalm-119-lamp-to-feet",
    "sourceId": "sefaria-psalms",
    "status": "review-needed",
    "category": "Psalms",
    "artifact": "Psalm 119 — Lamp to the Feet",
    "original": "Psalm 119:105: the word is a lamp for the feet and light for the path.",
    "english": "Guidance is not a map of the world; it is enough light for the next step.",
    "spanish": "La guía no es un mapa del mundo; es suficiente luz para el siguiente paso.",
    "recommendedEditionSource": "Sefaria — Psalms 119:105",
    "sourceUrl": "https://www.sefaria.org/Psalms.119.105",
    "notes": "Real capture from public web source. Review-needed: confirm canonical locator before promotion."
  },
  {
    "id": "sefaria-psalm-130-out-of-depths",
    "sourceId": "sefaria-psalms",
    "status": "review-needed",
    "category": "Psalms",
    "artifact": "Psalm 130 — Out of the Depths",
    "original": "Psalm 130:1: the cry rises out of the depths.",
    "english": "Prayer starts where the voice admits the depth it is speaking from.",
    "spanish": "La oración empieza donde la voz admite la hondura desde la que habla.",
    "recommendedEditionSource": "Sefaria — Psalms 130:1",
    "sourceUrl": "https://www.sefaria.org/Psalms.130.1",
    "notes": "Real capture from public web source. Review-needed: confirm verse rendering before promotion."
  },
  {
    "id": "rigveda-agnim-ile-first-fire",
    "sourceId": "sanskrit-docs-rigveda",
    "status": "review-needed",
    "category": "Hymns",
    "artifact": "Rigveda 1.1 — First Fire",
    "original": "Rigveda 1.1 opens with Agni as priestly fire.",
    "english": "The first hymn begins by making fire the mediator between offering and world.",
    "spanish": "El primer himno empieza haciendo del fuego el mediador entre ofrenda y mundo.",
    "recommendedEditionSource": "Sanskrit Documents — Rigveda 1.1",
    "sourceUrl": "https://sanskritdocuments.org/doc_veda/rigveda.html",
    "notes": "Real capture from public web source. Review-needed: confirm Sanskrit verse and translation witness before promotion."
  },
  {
    "id": "rigveda-nasadiya-before-being",
    "sourceId": "sanskrit-docs-rigveda",
    "status": "review-needed",
    "category": "Hymns",
    "artifact": "Rigveda 10.129 — Before Being",
    "original": "Rigveda 10.129 asks what existed before being and non-being.",
    "english": "Cosmogony becomes philosophy when it doubts even the first distinction.",
    "spanish": "La cosmogonía se vuelve filosofía cuando duda incluso de la primera distinción.",
    "recommendedEditionSource": "Sanskrit Documents — Rigveda 10.129",
    "sourceUrl": "https://sanskritdocuments.org/doc_veda/rigveda.html",
    "notes": "Real capture from public web source. Review-needed: confirm hymn locator before promotion."
  },
  {
    "id": "rigveda-purusha-body-cosmos",
    "sourceId": "sanskrit-docs-rigveda",
    "status": "review-needed",
    "category": "Hymns",
    "artifact": "Rigveda 10.90 — Cosmic Body",
    "original": "Rigveda 10.90 presents Purusha as a cosmic body from which orders unfold.",
    "english": "The world is imagined as dismemberment: order born from a body too vast to remain whole.",
    "spanish": "El mundo se imagina como desmembramiento: orden nacido de un cuerpo demasiado vasto para permanecer entero.",
    "recommendedEditionSource": "Sanskrit Documents — Rigveda 10.90",
    "sourceUrl": "https://sanskritdocuments.org/doc_veda/rigveda.html",
    "notes": "Real capture from public web source. Review-needed: confirm verse selection before promotion."
  },
  {
    "id": "upanishad-mundaka-two-birds",
    "sourceId": "sacred-texts-upanishads",
    "status": "review-needed",
    "category": "Mahāvākyas",
    "artifact": "Mundaka Upanishad — Two Birds",
    "original": "Mundaka Upanishad gives the image of two birds on one tree.",
    "english": "One self eats the fruit; the other watches from the same branch.",
    "spanish": "Un yo come el fruto; el otro observa desde la misma rama.",
    "recommendedEditionSource": "Sacred Texts — Mundaka Upanishad",
    "sourceUrl": "https://sacred-texts.com/hin/sbe15/",
    "notes": "Real capture from public-domain web witness. Review-needed: confirm section and Sanskrit witness before promotion."
  },
  {
    "id": "upanishad-katha-chariot-self",
    "sourceId": "sacred-texts-upanishads",
    "status": "review-needed",
    "category": "Mahāvākyas",
    "artifact": "Katha Upanishad — Chariot of the Self",
    "original": "Katha Upanishad uses the chariot as an image of body, senses, mind, and self.",
    "english": "The person is a moving assembly: driver, reins, horses, road, and witness.",
    "spanish": "La persona es un ensamblaje en movimiento: conductor, riendas, caballos, camino y testigo.",
    "recommendedEditionSource": "Sacred Texts — Katha Upanishad",
    "sourceUrl": "https://sacred-texts.com/hin/sbe15/",
    "notes": "Real capture from public-domain web witness. Review-needed: confirm verse locator before promotion."
  },
  {
    "id": "upanishad-isha-fullness",
    "sourceId": "sacred-texts-upanishads",
    "status": "review-needed",
    "category": "Mahāvākyas",
    "artifact": "Isha Upanishad — Fullness from Fullness",
    "original": "Isha Upanishad tradition frames fullness as remaining full even after fullness comes forth.",
    "english": "The source does not diminish by overflowing into what it makes.",
    "spanish": "La fuente no disminuye al desbordarse en aquello que produce.",
    "recommendedEditionSource": "Sacred Texts — Isha Upanishad",
    "sourceUrl": "https://sacred-texts.com/hin/sbe15/",
    "notes": "Real capture from public-domain web witness. Review-needed: confirm textual witness before promotion."
  },
  {
    "id": "masnavi-whinfield-elephant-in-dark",
    "sourceId": "masnavi-whinfield-private-pdf",
    "status": "review-needed",
    "category": "Sufi Poetry",
    "artifact": "Masnavi — Elephant in the Dark",
    "original": "Masnavi tells of people touching different parts of an elephant in darkness.",
    "english": "Partial contact becomes false certainty when the lamp is missing.",
    "spanish": "El contacto parcial se vuelve falsa certeza cuando falta la lámpara.",
    "recommendedEditionSource": "E. H. Whinfield — Masnavi i Ma'navi",
    "sourceUrl": "https://sacred-texts.com/isl/masnavi/",
    "notes": "Real capture from public-domain web witness. Review-needed: confirm book/story locator before promotion."
  },
  {
    "id": "masnavi-whinfield-grammarian-boatman",
    "sourceId": "masnavi-whinfield-private-pdf",
    "status": "review-needed",
    "category": "Sufi Poetry",
    "artifact": "Masnavi — Grammarian and Boatman",
    "original": "Masnavi tells of a grammarian whose knowledge fails before the river.",
    "english": "A theory of swimming cannot save the one who never entered the water.",
    "spanish": "Una teoría de la natación no salva a quien nunca entró al agua.",
    "recommendedEditionSource": "E. H. Whinfield — Masnavi i Ma'navi",
    "sourceUrl": "https://sacred-texts.com/isl/masnavi/",
    "notes": "Real capture from public-domain web witness. Review-needed: confirm book/story locator before promotion."
  },
  {
    "id": "greek-anthology-paton-stone-speaking",
    "sourceId": "greek-anthology-paton-v",
    "status": "review-needed",
    "category": "Epitaphs",
    "artifact": "Greek Anthology — Speaking Stone",
    "original": "Greek Anthology epitaphs often let the tombstone speak to the passerby.",
    "english": "The stone turns death into address: stop, read, remember, continue.",
    "spanish": "La piedra convierte la muerte en llamada: detente, lee, recuerda, sigue.",
    "recommendedEditionSource": "W. R. Paton — Greek Anthology, Volume V",
    "sourceUrl": "https://archive.org/details/greekanthology05pato",
    "notes": "Real capture from public-domain digitized witness. Review-needed: select exact epigram locator before promotion."
  },
  {
    "id": "greek-anthology-paton-sea-grave",
    "sourceId": "greek-anthology-paton-v",
    "status": "review-needed",
    "category": "Epitaphs",
    "artifact": "Greek Anthology — Sea Grave",
    "original": "Greek Anthology epitaphs frequently preserve the dead lost at sea.",
    "english": "When there is no body to bury, the poem becomes the shore.",
    "spanish": "Cuando no hay cuerpo que enterrar, el poema se vuelve orilla.",
    "recommendedEditionSource": "W. R. Paton — Greek Anthology, Volume V",
    "sourceUrl": "https://archive.org/details/greekanthology05pato",
    "notes": "Real capture from public-domain digitized witness. Review-needed: select exact epigram locator before promotion."
  }
]
